PyOpenWorm/__init__.py
PyOpenWorm/bibtex.py
PyOpenWorm/bibtex_customizations.py
PyOpenWorm/biology.py
PyOpenWorm/bittorrent.py
PyOpenWorm/capabilities.py
PyOpenWorm/capability.py
PyOpenWorm/cell.py
PyOpenWorm/cell_common.py
PyOpenWorm/channel.py
PyOpenWorm/channel_common.py
PyOpenWorm/channelworm.py
PyOpenWorm/cli.py
PyOpenWorm/cli_command_wrapper.py
PyOpenWorm/cli_common.py
PyOpenWorm/cli_hints.py
PyOpenWorm/collections.py
PyOpenWorm/command.py
PyOpenWorm/command_util.py
PyOpenWorm/configure.py
PyOpenWorm/connection.py
PyOpenWorm/context.py
PyOpenWorm/contextDataObject.py
PyOpenWorm/context_common.py
PyOpenWorm/context_store.py
PyOpenWorm/contextualize.py
PyOpenWorm/data.py
PyOpenWorm/dataObject.py
PyOpenWorm/datasource.py
PyOpenWorm/datasource_loader.py
PyOpenWorm/document.py
PyOpenWorm/documentContext.py
PyOpenWorm/evidence.py
PyOpenWorm/experiment.py
PyOpenWorm/git_repo.py
PyOpenWorm/identifier_mixin.py
PyOpenWorm/import_contextualizer.py
PyOpenWorm/import_override.py
PyOpenWorm/inverse_property.py
PyOpenWorm/mapper.py
PyOpenWorm/module_recorder.py
PyOpenWorm/muscle.py
PyOpenWorm/my_neuroml.py
PyOpenWorm/network.py
PyOpenWorm/neuron.py
PyOpenWorm/pProperty.py
PyOpenWorm/package_utils.py
PyOpenWorm/plot.py
PyOpenWorm/rdf_go_modifiers.py
PyOpenWorm/rdf_query_util.py
PyOpenWorm/simpleProperty.py
PyOpenWorm/statement.py
PyOpenWorm/text_util.py
PyOpenWorm/utils.py
PyOpenWorm/website.py
PyOpenWorm/worm.py
PyOpenWorm/worm_common.py
PyOpenWorm/data_trans/__init__.py
PyOpenWorm/data_trans/bibtex.py
PyOpenWorm/data_trans/common_data.py
PyOpenWorm/data_trans/connections.py
PyOpenWorm/data_trans/context_datasource.py
PyOpenWorm/data_trans/context_merge.py
PyOpenWorm/data_trans/csv_ds.py
PyOpenWorm/data_trans/data_with_evidence_ds.py
PyOpenWorm/data_trans/excel_ds.py
PyOpenWorm/data_trans/file_ds.py
PyOpenWorm/data_trans/http_ds.py
PyOpenWorm/data_trans/local_file_ds.py
PyOpenWorm/data_trans/neuron_data.py
PyOpenWorm/data_trans/wormatlas.py
PyOpenWorm/data_trans/wormbase.py
PyOpenWorm-0.11.3.dist-info/LICENSE.txt
PyOpenWorm-0.11.3.dist-info/METADATA
PyOpenWorm-0.11.3.dist-info/WHEEL
PyOpenWorm-0.11.3.dist-info/entry_points.txt
PyOpenWorm-0.11.3.dist-info/top_level.txt
PyOpenWorm-0.11.3.dist-info/RECORD
